fairtracks_validator/__init__.py
fairtracks_validator/downloader.py
fairtracks_validator/fairtracks_validator.py
fairtracks_validator/extensions/__init__.py
fairtracks_validator/extensions/curie_cache.py
fairtracks_validator/extensions/curie_search.py
fairtracks_validator/extensions/foreign_property_check.py
fairtracks_validator/extensions/ontology_term.py
fairtracks_validator-0.9.10.data/scripts/fairGTrackJsonValidate.py
fairtracks_validator-0.9.10.dist-info/LICENSE
fairtracks_validator-0.9.10.dist-info/METADATA
fairtracks_validator-0.9.10.dist-info/WHEEL
fairtracks_validator-0.9.10.dist-info/top_level.txt
fairtracks_validator-0.9.10.dist-info/RECORD
