Metadata-Version: 2.1
Name: fairtracks-validator
Version: 0.9.10
Summary: FAIRtracks JSON Validator
Home-page: https://github.com/fairtracks/fairtracks_validator_python
Author: José Mª Fernández
Author-email: jose.m.fernandez@bsc.es
License: LGPLv2
Project-URL: Bug Tracker, https://github.com/fairtracks/fairtracks_validator_python/issues
Platform: UNKNOWN
Classifier: Programming Language :: Python :: 3
Classifier: License :: OSI Approved :: GNU Lesser General Public License v2 (LGPLv2)
Classifier: Operating System :: OS Independent
Requires-Python: >=3.6
License-File: LICENSE
Requires-Dist: extended-json-schema-validator (>=0.9.11)
Requires-Dist: jsonschema[format] (>=3.0.0)
Requires-Dist: uritools
Requires-Dist: cython
Requires-Dist: owlready2 (>=0.23)
Requires-Dist: dateparser
Requires-Dist: pyyaml
